README.md
setup.py
mschematool/__init__.py
mschematool/cli.py
mschematool/core.py
mschematool.egg-info/PKG-INFO
mschematool.egg-info/SOURCES.txt
mschematool.egg-info/dependency_links.txt
mschematool.egg-info/entry_points.txt
mschematool.egg-info/requires.txt
mschematool.egg-info/top_level.txt
mschematool/executors/__init__.py
mschematool/executors/cassandradb.py
mschematool/executors/postgres.py
mschematool/executors/sqlite3db.py