Metadata-Version: 2.1
Name: mschematool
Version: 0.9.1
Summary: Minimal database schema migrations tool
Home-page: https://github.com/aartur/mschematool
Author: Artur Siekielski
Author-email: artur.siekielski@vhex.net
License: BSD
Keywords: database schema migrations postgresql postgres cassandra
Platform: UNKNOWN
Classifier: Topic :: Database
Classifier: Environment :: Console
Classifier: License :: OSI Approved :: BSD License
Classifier: Programming Language :: Python :: 2.7
Provides-Extra: postgresql
Provides-Extra: cassandra
